jpylyzer/__init__.py
jpylyzer/__main__.py
jpylyzer/boxvalidator.py
jpylyzer/byteconv.py
jpylyzer/config.py
jpylyzer/etpatch.py
jpylyzer/jpylyzer.py
jpylyzer/mix.py
jpylyzer/shared.py
jpylyzer-2.2.1.dist-info/LICENSE
jpylyzer-2.2.1.dist-info/METADATA
jpylyzer-2.2.1.dist-info/WHEEL
jpylyzer-2.2.1.dist-info/entry_points.txt
jpylyzer-2.2.1.dist-info/top_level.txt
jpylyzer-2.2.1.dist-info/RECORD
